{
  "schema": "v4",
  "meta": {
    "plan_code": "NUIW5903",
    "company": "台灣人壽",
    "product_name": "台灣人壽吉美得美元利率變動型終身壽險",
    "currency": "USD",
    "period": 1,
    "base_sa": 80774,
    "base_premium": 100000,
    "base_premium_gross": 100806,
    "base_age": 20,
    "base_sex": "M",
    "discount": 0.008,
    "discount_method": "simple",
    "declared_rate": 0.043,
    "guaranteed_rate": 0.015,
    "engine": "twlife_v1",
    "premium_mode": "lump_sum",
    "is_lump_sum_demo": true,
    "dividend_option": "購買增額繳清保險",
    "min_sa": 10000,
    "max_sa": 10000000,
    "min_age": 0,
    "max_age": 75,
    "_metadata_source": "index.html PRODUCTS (xlsm 解析未完成,等補 DM)"
  },
  "schedule": [
    {
      "y": 1,
      "age": 20,
      "cum_prem": 100000,
      "cv_basic": 71864.63,
      "cv_total": 74547.97,
      "sa_basic": 83036,
      "death_benefit": 187155.91,
      "increment_amount": 2262,
      "cv_increment": 2683.34
    },
    {
      "y": 2,
      "age": 21,
      "cum_prem": 100000,
      "cv_basic": 72913.88,
      "cv_total": 78434.7,
      "sa_basic": 85361,
      "death_benefit": 195203.71,
      "increment_amount": 4587,
      "cv_increment": 5520.82
    },
    {
      "y": 3,
      "age": 22,
      "cum_prem": 100000,
      "cv_basic": 97649.3,
      "cv_total": 106169.12,
      "sa_basic": 87751,
      "death_benefit": 203595.21,
      "increment_amount": 6977,
      "cv_increment": 8519.82
    },
    {
      "y": 4,
      "age": 23,
      "cum_prem": 100000,
      "cv_basic": 99072.54,
      "cv_total": 110760.61,
      "sa_basic": 90208,
      "death_benefit": 212346.66,
      "increment_amount": 9434,
      "cv_increment": 11688.07
    },
    {
      "y": 5,
      "age": 24,
      "cum_prem": 100000,
      "cv_basic": 100515.97,
      "cv_total": 115549.45,
      "sa_basic": 92734,
      "death_benefit": 221473.09,
      "increment_amount": 11960,
      "cv_increment": 15033.48
    },
    {
      "y": 6,
      "age": 25,
      "cum_prem": 100000,
      "cv_basic": 101978.79,
      "cv_total": 120542.9,
      "sa_basic": 95331,
      "death_benefit": 230988.27,
      "increment_amount": 14557,
      "cv_increment": 18564.11
    },
    {
      "y": 7,
      "age": 26,
      "cum_prem": 100000,
      "cv_basic": 104506.21,
      "cv_total": 126793.38,
      "sa_basic": 98000,
      "death_benefit": 240907.43,
      "increment_amount": 17226,
      "cv_increment": 22287.17
    },
    {
      "y": 8,
      "age": 27,
      "cum_prem": 100000,
      "cv_basic": 106023.95,
      "cv_total": 132236.57,
      "sa_basic": 100744,
      "death_benefit": 251249.49,
      "increment_amount": 19970,
      "cv_increment": 26212.62
    },
    {
      "y": 9,
      "age": 28,
      "cum_prem": 100000,
      "cv_basic": 107562.7,
      "cv_total": 137912.34,
      "sa_basic": 103565,
      "death_benefit": 262033.45,
      "increment_amount": 22791,
      "cv_increment": 30349.64
    },
    {
      "y": 10,
      "age": 29,
      "cum_prem": 100000,
      "cv_basic": 109120.02,
      "cv_total": 143826.76,
      "sa_basic": 106465,
      "death_benefit": 273270.85,
      "increment_amount": 25691,
      "cv_increment": 34706.74
    },
    {
      "y": 11,
      "age": 30,
      "cum_prem": 100000,
      "cv_basic": 110691.88,
      "cv_total": 149983.7,
      "sa_basic": 109446,
      "death_benefit": 284969.03,
      "increment_amount": 28672,
      "cv_increment": 39291.82
    },
    {
      "y": 12,
      "age": 31,
      "cum_prem": 100000,
      "cv_basic": 112304.94,
      "cv_total": 156429.4,
      "sa_basic": 112510,
      "death_benefit": 250287.04,
      "increment_amount": 31736,
      "cv_increment": 44124.46
    },
    {
      "y": 13,
      "age": 32,
      "cum_prem": 100000,
      "cv_basic": 113938.19,
      "cv_total": 163147.68,
      "sa_basic": 115660,
      "death_benefit": 261036.29,
      "increment_amount": 34886,
      "cv_increment": 49209.49
    },
    {
      "y": 14,
      "age": 33,
      "cum_prem": 100000,
      "cv_basic": 115591.63,
      "cv_total": 170148.98,
      "sa_basic": 118898,
      "death_benefit": 272238.37,
      "increment_amount": 38124,
      "cv_increment": 54557.35
    },
    {
      "y": 15,
      "age": 34,
      "cum_prem": 100000,
      "cv_basic": 117263.65,
      "cv_total": 177443.04,
      "sa_basic": 122227,
      "death_benefit": 283908.87,
      "increment_amount": 41453,
      "cv_increment": 60179.39
    },
    {
      "y": 16,
      "age": 35,
      "cum_prem": 100000,
      "cv_basic": 118952.64,
      "cv_total": 185038.26,
      "sa_basic": 125649,
      "death_benefit": 296061.22,
      "increment_amount": 44875,
      "cv_increment": 66085.62
    },
    {
      "y": 17,
      "age": 36,
      "cum_prem": 100000,
      "cv_basic": 120660.2,
      "cv_total": 192949.66,
      "sa_basic": 129167,
      "death_benefit": 308719.46,
      "increment_amount": 48393,
      "cv_increment": 72289.46
    },
    {
      "y": 18,
      "age": 37,
      "cum_prem": 100000,
      "cv_basic": 122384.73,
      "cv_total": 201187.68,
      "sa_basic": 132784,
      "death_benefit": 321900.29,
      "increment_amount": 52010,
      "cv_increment": 78802.95
    },
    {
      "y": 19,
      "age": 38,
      "cum_prem": 100000,
      "cv_basic": 124125.41,
      "cv_total": 209762.63,
      "sa_basic": 136502,
      "death_benefit": 335620.21,
      "increment_amount": 55728,
      "cv_increment": 85637.22
    },
    {
      "y": 20,
      "age": 39,
      "cum_prem": 100000,
      "cv_basic": 125883.05,
      "cv_total": 218689.34,
      "sa_basic": 140324,
      "death_benefit": 349902.95,
      "increment_amount": 59550,
      "cv_increment": 92806.29
    },
    {
      "y": 21,
      "age": 40,
      "cum_prem": 100000,
      "cv_basic": 127653.61,
      "cv_total": 227974.55,
      "sa_basic": 144253,
      "death_benefit": 364759.28,
      "increment_amount": 63479,
      "cv_increment": 100320.94
    },
    {
      "y": 22,
      "age": 41,
      "cum_prem": 100000,
      "cv_basic": 129482.34,
      "cv_total": 237715.04,
      "sa_basic": 148292,
      "death_benefit": 332801.06,
      "increment_amount": 67518,
      "cv_increment": 108232.7
    },
    {
      "y": 23,
      "age": 42,
      "cum_prem": 100000,
      "cv_basic": 131328.83,
      "cv_total": 247855.65,
      "sa_basic": 152444,
      "death_benefit": 346997.91,
      "increment_amount": 71670,
      "cv_increment": 116526.82
    },
    {
      "y": 24,
      "age": 43,
      "cum_prem": 100000,
      "cv_basic": 133193.9,
      "cv_total": 258413.38,
      "sa_basic": 156712,
      "death_benefit": 361778.74,
      "increment_amount": 75938,
      "cv_increment": 125219.48
    },
    {
      "y": 25,
      "age": 44,
      "cum_prem": 100000,
      "cv_basic": 135075.94,
      "cv_total": 269402.7,
      "sa_basic": 161100,
      "death_benefit": 377163.78,
      "increment_amount": 80326,
      "cv_increment": 134326.76
    },
    {
      "y": 26,
      "age": 45,
      "cum_prem": 100000,
      "cv_basic": 136969.28,
      "cv_total": 280828.23,
      "sa_basic": 165611,
      "death_benefit": 393159.53,
      "increment_amount": 84837,
      "cv_increment": 143858.95
    },
    {
      "y": 27,
      "age": 46,
      "cum_prem": 100000,
      "cv_basic": 138878.78,
      "cv_total": 292715.9,
      "sa_basic": 170248,
      "death_benefit": 409802.26,
      "increment_amount": 89474,
      "cv_increment": 153837.12
    },
    {
      "y": 28,
      "age": 47,
      "cum_prem": 100000,
      "cv_basic": 140803.62,
      "cv_total": 305082.65,
      "sa_basic": 175015,
      "death_benefit": 427115.71,
      "increment_amount": 94241,
      "cv_increment": 164279.03
    },
    {
      "y": 29,
      "age": 48,
      "cum_prem": 100000,
      "cv_basic": 142742.2,
      "cv_total": 317942.19,
      "sa_basic": 179915,
      "death_benefit": 445119.07,
      "increment_amount": 99141,
      "cv_increment": 175199.99
    },
    {
      "y": 30,
      "age": 49,
      "cum_prem": 100000,
      "cv_basic": 144695.31,
      "cv_total": 331317.4,
      "sa_basic": 184953,
      "death_benefit": 463844.36,
      "increment_amount": 104179,
      "cv_increment": 186622.09
    },
    {
      "y": 31,
      "age": 50,
      "cum_prem": 100000,
      "cv_basic": 146662.16,
      "cv_total": 345224.57,
      "sa_basic": 190132,
      "death_benefit": 483314.4,
      "increment_amount": 109358,
      "cv_increment": 198562.41
    },
    {
      "y": 32,
      "age": 51,
      "cum_prem": 100000,
      "cv_basic": 148750.98,
      "cv_total": 359945.91,
      "sa_basic": 195456,
      "death_benefit": 431935.1,
      "increment_amount": 114682,
      "cv_increment": 211194.93
    },
    {
      "y": 33,
      "age": 52,
      "cum_prem": 100000,
      "cv_basic": 150861.6,
      "cv_total": 375275.09,
      "sa_basic": 200929,
      "death_benefit": 450330.11,
      "increment_amount": 120155,
      "cv_increment": 224413.49
    },
    {
      "y": 34,
      "age": 53,
      "cum_prem": 100000,
      "cv_basic": 152993.23,
      "cv_total": 391233.76,
      "sa_basic": 206555,
      "death_benefit": 469480.52,
      "increment_amount": 125781,
      "cv_increment": 238240.53
    },
    {
      "y": 35,
      "age": 54,
      "cum_prem": 100000,
      "cv_basic": 155145.85,
      "cv_total": 407848.01,
      "sa_basic": 212339,
      "death_benefit": 489417.62,
      "increment_amount": 131565,
      "cv_increment": 252702.16
    },
    {
      "y": 36,
      "age": 55,
      "cum_prem": 100000,
      "cv_basic": 157313.02,
      "cv_total": 425123.37,
      "sa_basic": 218284,
      "death_benefit": 510148.05,
      "increment_amount": 137510,
      "cv_increment": 267810.35
    },
    {
      "y": 37,
      "age": 56,
      "cum_prem": 100000,
      "cv_basic": 159499.57,
      "cv_total": 443101.32,
      "sa_basic": 224396,
      "death_benefit": 531721.59,
      "increment_amount": 143622,
      "cv_increment": 283601.75
    },
    {
      "y": 38,
      "age": 57,
      "cum_prem": 100000,
      "cv_basic": 161703.89,
      "cv_total": 461803.21,
      "sa_basic": 230679,
      "death_benefit": 554163.86,
      "increment_amount": 149905,
      "cv_increment": 300099.32
    },
    {
      "y": 39,
      "age": 58,
      "cum_prem": 100000,
      "cv_basic": 163924.37,
      "cv_total": 481252.6,
      "sa_basic": 237138,
      "death_benefit": 577503.12,
      "increment_amount": 156364,
      "cv_increment": 317328.23
    },
    {
      "y": 40,
      "age": 59,
      "cum_prem": 100000,
      "cv_basic": 166160.2,
      "cv_total": 501475.73,
      "sa_basic": 243778,
      "death_benefit": 601770.88,
      "increment_amount": 163004,
      "cv_increment": 335315.53
    },
    {
      "y": 41,
      "age": 60,
      "cum_prem": 100000,
      "cv_basic": 168400.06,
      "cv_total": 522466.74,
      "sa_basic": 250604,
      "death_benefit": 626960.09,
      "increment_amount": 169830,
      "cv_increment": 354066.68
    },
    {
      "y": 42,
      "age": 61,
      "cum_prem": 100000,
      "cv_basic": 170789.35,
      "cv_total": 544716.42,
      "sa_basic": 257621,
      "death_benefit": 599188.07,
      "increment_amount": 176847,
      "cv_increment": 373927.07
    },
    {
      "y": 43,
      "age": 62,
      "cum_prem": 100000,
      "cv_basic": 173201.26,
      "cv_total": 567875.6,
      "sa_basic": 264834,
      "death_benefit": 624663.16,
      "increment_amount": 184060,
      "cv_increment": 394674.34
    },
    {
      "y": 44,
      "age": 63,
      "cum_prem": 100000,
      "cv_basic": 175634.99,
      "cv_total": 591978.23,
      "sa_basic": 272249,
      "death_benefit": 651176.06,
      "increment_amount": 191475,
      "cv_increment": 416343.24
    },
    {
      "y": 45,
      "age": 64,
      "cum_prem": 100000,
      "cv_basic": 178089.71,
      "cv_total": 617058.99,
      "sa_basic": 279872,
      "death_benefit": 678764.89,
      "increment_amount": 199098,
      "cv_increment": 438969.28
    },
    {
      "y": 46,
      "age": 65,
      "cum_prem": 100000,
      "cv_basic": 180556.55,
      "cv_total": 643122.33,
      "sa_basic": 287708,
      "death_benefit": 707434.57,
      "increment_amount": 206934,
      "cv_increment": 462565.78
    },
    {
      "y": 47,
      "age": 66,
      "cum_prem": 100000,
      "cv_basic": 183039.54,
      "cv_total": 670221.93,
      "sa_basic": 295764,
      "death_benefit": 737244.13,
      "increment_amount": 214990,
      "cv_increment": 487182.39
    },
    {
      "y": 48,
      "age": 67,
      "cum_prem": 100000,
      "cv_basic": 185535.45,
      "cv_total": 698382.24,
      "sa_basic": 304045,
      "death_benefit": 768220.47,
      "increment_amount": 223271,
      "cv_increment": 512846.79
    },
    {
      "y": 49,
      "age": 68,
      "cum_prem": 100000,
      "cv_basic": 188041.06,
      "cv_total": 727631.89,
      "sa_basic": 312558,
      "death_benefit": 800395.08,
      "increment_amount": 231784,
      "cv_increment": 539590.83
    },
    {
      "y": 50,
      "age": 69,
      "cum_prem": 100000,
      "cv_basic": 190553.94,
      "cv_total": 758002.42,
      "sa_basic": 321310,
      "death_benefit": 833802.67,
      "increment_amount": 240536,
      "cv_increment": 567448.48
    },
    {
      "y": 51,
      "age": 70,
      "cum_prem": 100000,
      "cv_basic": 193050.67,
      "cv_total": 789437.04,
      "sa_basic": 330307,
      "death_benefit": 868380.75,
      "increment_amount": 249533,
      "cv_increment": 596386.37
    },
    {
      "y": 52,
      "age": 71,
      "cum_prem": 100000,
      "cv_basic": 195866.45,
      "cv_total": 823379.16,
      "sa_basic": 339556,
      "death_benefit": 839846.75,
      "increment_amount": 258782,
      "cv_increment": 627512.71
    },
    {
      "y": 53,
      "age": 72,
      "cum_prem": 100000,
      "cv_basic": 198715.35,
      "cv_total": 858746.31,
      "sa_basic": 349064,
      "death_benefit": 875921.24,
      "increment_amount": 268290,
      "cv_increment": 660030.96
    },
    {
      "y": 54,
      "age": 73,
      "cum_prem": 100000,
      "cv_basic": 201597.36,
      "cv_total": 895595.05,
      "sa_basic": 358838,
      "death_benefit": 913506.96,
      "increment_amount": 278064,
      "cv_increment": 693997.69
    },
    {
      "y": 55,
      "age": 74,
      "cum_prem": 100000,
      "cv_basic": 204511.69,
      "cv_total": 933979.93,
      "sa_basic": 368885,
      "death_benefit": 952659.53,
      "increment_amount": 288111,
      "cv_increment": 729468.24
    },
    {
      "y": 56,
      "age": 75,
      "cum_prem": 100000,
      "cv_basic": 207458.33,
      "cv_total": 973965.66,
      "sa_basic": 379214,
      "death_benefit": 993444.98,
      "increment_amount": 298440,
      "cv_increment": 766507.33
    },
    {
      "y": 57,
      "age": 76,
      "cum_prem": 100000,
      "cv_basic": 210435.66,
      "cv_total": 1015605.92,
      "sa_basic": 389832,
      "death_benefit": 1035918.04,
      "increment_amount": 309058,
      "cv_increment": 805170.26
    },
    {
      "y": 58,
      "age": 77,
      "cum_prem": 100000,
      "cv_basic": 213442.87,
      "cv_total": 1058961.92,
      "sa_basic": 400747,
      "death_benefit": 1080141.16,
      "increment_amount": 319973,
      "cv_increment": 845519.05
    },
    {
      "y": 59,
      "age": 78,
      "cum_prem": 100000,
      "cv_basic": 216477.55,
      "cv_total": 1104090.72,
      "sa_basic": 411968,
      "death_benefit": 1126172.54,
      "increment_amount": 331194,
      "cv_increment": 887613.17
    },
    {
      "y": 60,
      "age": 79,
      "cum_prem": 100000,
      "cv_basic": 219539.69,
      "cv_total": 1151059.98,
      "sa_basic": 423503,
      "death_benefit": 1174081.18,
      "increment_amount": 342729,
      "cv_increment": 931520.29
    },
    {
      "y": 61,
      "age": 80,
      "cum_prem": 100000,
      "cv_basic": 222626.07,
      "cv_total": 1199924.58,
      "sa_basic": 435361,
      "death_benefit": 1223923.08,
      "increment_amount": 354587,
      "cv_increment": 977298.51
    },
    {
      "y": 62,
      "age": 81,
      "cum_prem": 100000,
      "cv_basic": 225736.67,
      "cv_total": 1250757.35,
      "sa_basic": 447551,
      "death_benefit": 1275772.5,
      "increment_amount": 366777,
      "cv_increment": 1025020.68
    },
    {
      "y": 63,
      "age": 82,
      "cum_prem": 100000,
      "cv_basic": 228869.09,
      "cv_total": 1303619.34,
      "sa_basic": 460082,
      "death_benefit": 1329691.73,
      "increment_amount": 379308,
      "cv_increment": 1074750.25
    },
    {
      "y": 64,
      "age": 83,
      "cum_prem": 100000,
      "cv_basic": 232020.08,
      "cv_total": 1358570.17,
      "sa_basic": 472964,
      "death_benefit": 1385741.58,
      "increment_amount": 392190,
      "cv_increment": 1126550.09
    },
    {
      "y": 65,
      "age": 84,
      "cum_prem": 100000,
      "cv_basic": 235187.23,
      "cv_total": 1415674.33,
      "sa_basic": 486207,
      "death_benefit": 1443987.82,
      "increment_amount": 405433,
      "cv_increment": 1180487.1
    },
    {
      "y": 66,
      "age": 85,
      "cum_prem": 100000,
      "cv_basic": 238368.11,
      "cv_total": 1474996.76,
      "sa_basic": 499821,
      "death_benefit": 1504496.7,
      "increment_amount": 419047,
      "cv_increment": 1236628.65
    },
    {
      "y": 67,
      "age": 86,
      "cum_prem": 100000,
      "cv_basic": 241557.88,
      "cv_total": 1536587.3,
      "sa_basic": 513816,
      "death_benefit": 1567319.05,
      "increment_amount": 433042,
      "cv_increment": 1295029.42
    },
    {
      "y": 68,
      "age": 87,
      "cum_prem": 100000,
      "cv_basic": 244751.68,
      "cv_total": 1600497.34,
      "sa_basic": 528203,
      "death_benefit": 1632507.29,
      "increment_amount": 447429,
      "cv_increment": 1355745.66
    },
    {
      "y": 69,
      "age": 88,
      "cum_prem": 100000,
      "cv_basic": 247946.29,
      "cv_total": 1666787.6,
      "sa_basic": 542993,
      "death_benefit": 1700123.36,
      "increment_amount": 462219,
      "cv_increment": 1418841.31
    },
    {
      "y": 70,
      "age": 89,
      "cum_prem": 100000,
      "cv_basic": 251138.48,
      "cv_total": 1735518.2,
      "sa_basic": 558197,
      "death_benefit": 1770228.57,
      "increment_amount": 477423,
      "cv_increment": 1484379.72
    },
    {
      "y": 71,
      "age": 90,
      "cum_prem": 100000,
      "cv_basic": 254318.55,
      "cv_total": 1806705.78,
      "sa_basic": 573827,
      "death_benefit": 1842839.9,
      "increment_amount": 493053,
      "cv_increment": 1552387.23
    },
    {
      "y": 72,
      "age": 91,
      "cum_prem": 100000,
      "cv_basic": 258132.7,
      "cv_total": 1885147.85,
      "sa_basic": 589894,
      "death_benefit": 1885147.85,
      "increment_amount": 509120,
      "cv_increment": 1627015.15
    },
    {
      "y": 73,
      "age": 92,
      "cum_prem": 100000,
      "cv_basic": 262003.39,
      "cv_total": 1966991.1,
      "sa_basic": 606411,
      "death_benefit": 1966991.1,
      "increment_amount": 525637,
      "cv_increment": 1704987.71
    },
    {
      "y": 74,
      "age": 93,
      "cum_prem": 100000,
      "cv_basic": 265933.05,
      "cv_total": 2052396.43,
      "sa_basic": 623391,
      "death_benefit": 2052396.43,
      "increment_amount": 542617,
      "cv_increment": 1786463.38
    },
    {
      "y": 75,
      "age": 94,
      "cum_prem": 100000,
      "cv_basic": 269920.86,
      "cv_total": 2141502.26,
      "sa_basic": 640846,
      "death_benefit": 2141502.26,
      "increment_amount": 560072,
      "cv_increment": 1871581.4
    },
    {
      "y": 76,
      "age": 95,
      "cum_prem": 100000,
      "cv_basic": 273967.64,
      "cv_total": 2234470.75,
      "sa_basic": 658790,
      "death_benefit": 2234470.75,
      "increment_amount": 578016,
      "cv_increment": 1960503.11
    },
    {
      "y": 77,
      "age": 96,
      "cum_prem": 100000,
      "cv_basic": 278075.8,
      "cv_total": 2331479.74,
      "sa_basic": 677236,
      "death_benefit": 2331479.74,
      "increment_amount": 596462,
      "cv_increment": 2053403.94
    },
    {
      "y": 78,
      "age": 97,
      "cum_prem": 100000,
      "cv_basic": 282245.36,
      "cv_total": 2432700.32,
      "sa_basic": 696199,
      "death_benefit": 2432700.32,
      "increment_amount": 615425,
      "cv_increment": 2150454.96
    },
    {
      "y": 79,
      "age": 98,
      "cum_prem": 100000,
      "cv_basic": 286477.11,
      "cv_total": 2538312.58,
      "sa_basic": 715693,
      "death_benefit": 2538312.58,
      "increment_amount": 634919,
      "cv_increment": 2251835.47
    },
    {
      "y": 80,
      "age": 99,
      "cum_prem": 100000,
      "cv_basic": 290771.86,
      "cv_total": 2648502.77,
      "sa_basic": 735732,
      "death_benefit": 2648502.77,
      "increment_amount": 654958,
      "cv_increment": 2357730.91
    },
    {
      "y": 81,
      "age": 100,
      "cum_prem": 100000,
      "cv_basic": 295131.23,
      "cv_total": 2763478.29,
      "sa_basic": 756332,
      "death_benefit": 2763478.29,
      "increment_amount": 675558,
      "cv_increment": 2468347.06
    },
    {
      "y": 82,
      "age": 101,
      "cum_prem": 100000,
      "cv_basic": 299555.23,
      "cv_total": 2883438.78,
      "sa_basic": 777509,
      "death_benefit": 2883438.78,
      "increment_amount": 696735,
      "cv_increment": 2583883.55
    },
    {
      "y": 83,
      "age": 102,
      "cum_prem": 100000,
      "cv_basic": 304045.45,
      "cv_total": 3008606.05,
      "sa_basic": 799279,
      "death_benefit": 3008606.05,
      "increment_amount": 718505,
      "cv_increment": 2704560.6
    },
    {
      "y": 84,
      "age": 103,
      "cum_prem": 100000,
      "cv_basic": 308602.72,
      "cv_total": 3139205.72,
      "sa_basic": 821659,
      "death_benefit": 3139205.72,
      "increment_amount": 740885,
      "cv_increment": 2830603
    },
    {
      "y": 85,
      "age": 104,
      "cum_prem": 100000,
      "cv_basic": 313228.65,
      "cv_total": 3275475.73,
      "sa_basic": 844665,
      "death_benefit": 3275475.73,
      "increment_amount": 763891,
      "cv_increment": 2962247.08
    },
    {
      "y": 86,
      "age": 105,
      "cum_prem": 100000,
      "cv_basic": 317922.43,
      "cv_total": 3417648.36,
      "sa_basic": 868316,
      "death_benefit": 3417648.36,
      "increment_amount": 787542,
      "cv_increment": 3099725.93
    },
    {
      "y": 87,
      "age": 106,
      "cum_prem": 100000,
      "cv_basic": 322686.48,
      "cv_total": 3565990.38,
      "sa_basic": 892629,
      "death_benefit": 3565990.38,
      "increment_amount": 811855,
      "cv_increment": 3243303.9
    },
    {
      "y": 88,
      "age": 107,
      "cum_prem": 100000,
      "cv_basic": 327521.61,
      "cv_total": 3720768.57,
      "sa_basic": 917623,
      "death_benefit": 3720768.57,
      "increment_amount": 836849,
      "cv_increment": 3393246.96
    },
    {
      "y": 89,
      "age": 108,
      "cum_prem": 100000,
      "cv_basic": 332427.82,
      "cv_total": 3882245.3,
      "sa_basic": 943316,
      "death_benefit": 3882245.3,
      "increment_amount": 862542,
      "cv_increment": 3549817.48
    },
    {
      "y": 90,
      "age": 109,
      "cum_prem": 100000,
      "cv_basic": 337407.54,
      "cv_total": 4050732.59,
      "sa_basic": 969729,
      "death_benefit": 4050732.59,
      "increment_amount": 888955,
      "cv_increment": 3713325.05
    },
    {
      "y": 91,
      "age": 110,
      "cum_prem": 100000,
      "cv_basic": 0,
      "cv_total": 0,
      "sa_basic": 996881,
      "death_benefit": 4226376.69,
      "increment_amount": 916107,
      "cv_increment": 0
    }
  ],
  "schedule_low": [
    {
      "y": 1,
      "age": 20,
      "cum_prem": 100000,
      "cv_basic": 71864.63,
      "cv_total": 71864.63,
      "sa_basic": 80774,
      "death_benefit": 182057.57,
      "increment_amount": 0,
      "cv_increment": 0
    },
    {
      "y": 2,
      "age": 21,
      "cum_prem": 100000,
      "cv_basic": 72913.88,
      "cv_total": 72913.88,
      "sa_basic": 80774,
      "death_benefit": 184714.15,
      "increment_amount": 0,
      "cv_increment": 0
    },
    {
      "y": 3,
      "age": 22,
      "cum_prem": 100000,
      "cv_basic": 97649.3,
      "cv_total": 97649.3,
      "sa_basic": 80774,
      "death_benefit": 187407.55,
      "increment_amount": 0,
      "cv_increment": 0
    },
    {
      "y": 4,
      "age": 23,
      "cum_prem": 100000,
      "cv_basic": 99072.54,
      "cv_total": 99072.54,
      "sa_basic": 80774,
      "death_benefit": 190139.33,
      "increment_amount": 0,
      "cv_increment": 0
    },
    {
      "y": 5,
      "age": 24,
      "cum_prem": 100000,
      "cv_basic": 100515.97,
      "cv_total": 100515.97,
      "sa_basic": 80774,
      "death_benefit": 192909.47,
      "increment_amount": 0,
      "cv_increment": 0
    },
    {
      "y": 6,
      "age": 25,
      "cum_prem": 100000,
      "cv_basic": 101978.79,
      "cv_total": 101978.79,
      "sa_basic": 80774,
      "death_benefit": 195716.46,
      "increment_amount": 0,
      "cv_increment": 0
    },
    {
      "y": 7,
      "age": 26,
      "cum_prem": 100000,
      "cv_basic": 104506.21,
      "cv_total": 104506.21,
      "sa_basic": 80774,
      "death_benefit": 198561.8,
      "increment_amount": 0,
      "cv_increment": 0
    },
    {
      "y": 8,
      "age": 27,
      "cum_prem": 100000,
      "cv_basic": 106023.95,
      "cv_total": 106023.95,
      "sa_basic": 80774,
      "death_benefit": 201445.51,
      "increment_amount": 0,
      "cv_increment": 0
    },
    {
      "y": 9,
      "age": 28,
      "cum_prem": 100000,
      "cv_basic": 107562.7,
      "cv_total": 107562.7,
      "sa_basic": 80774,
      "death_benefit": 204369.13,
      "increment_amount": 0,
      "cv_increment": 0
    },
    {
      "y": 10,
      "age": 29,
      "cum_prem": 100000,
      "cv_basic": 109120.02,
      "cv_total": 109120.02,
      "sa_basic": 80774,
      "death_benefit": 207328.04,
      "increment_amount": 0,
      "cv_increment": 0
    },
    {
      "y": 11,
      "age": 30,
      "cum_prem": 100000,
      "cv_basic": 110691.88,
      "cv_total": 110691.88,
      "sa_basic": 80774,
      "death_benefit": 210314.58,
      "increment_amount": 0,
      "cv_increment": 0
    },
    {
      "y": 12,
      "age": 31,
      "cum_prem": 100000,
      "cv_basic": 112304.94,
      "cv_total": 112304.94,
      "sa_basic": 80774,
      "death_benefit": 179687.91,
      "increment_amount": 0,
      "cv_increment": 0
    },
    {
      "y": 13,
      "age": 32,
      "cum_prem": 100000,
      "cv_basic": 113938.19,
      "cv_total": 113938.19,
      "sa_basic": 80774,
      "death_benefit": 182301.11,
      "increment_amount": 0,
      "cv_increment": 0
    },
    {
      "y": 14,
      "age": 33,
      "cum_prem": 100000,
      "cv_basic": 115591.63,
      "cv_total": 115591.63,
      "sa_basic": 80774,
      "death_benefit": 184946.61,
      "increment_amount": 0,
      "cv_increment": 0
    },
    {
      "y": 15,
      "age": 34,
      "cum_prem": 100000,
      "cv_basic": 117263.65,
      "cv_total": 117263.65,
      "sa_basic": 80774,
      "death_benefit": 187621.84,
      "increment_amount": 0,
      "cv_increment": 0
    },
    {
      "y": 16,
      "age": 35,
      "cum_prem": 100000,
      "cv_basic": 118952.64,
      "cv_total": 118952.64,
      "sa_basic": 80774,
      "death_benefit": 190324.23,
      "increment_amount": 0,
      "cv_increment": 0
    },
    {
      "y": 17,
      "age": 36,
      "cum_prem": 100000,
      "cv_basic": 120660.2,
      "cv_total": 120660.2,
      "sa_basic": 80774,
      "death_benefit": 193056.32,
      "increment_amount": 0,
      "cv_increment": 0
    },
    {
      "y": 18,
      "age": 37,
      "cum_prem": 100000,
      "cv_basic": 122384.73,
      "cv_total": 122384.73,
      "sa_basic": 80774,
      "death_benefit": 195815.57,
      "increment_amount": 0,
      "cv_increment": 0
    },
    {
      "y": 19,
      "age": 38,
      "cum_prem": 100000,
      "cv_basic": 124125.41,
      "cv_total": 124125.41,
      "sa_basic": 80774,
      "death_benefit": 198600.66,
      "increment_amount": 0,
      "cv_increment": 0
    },
    {
      "y": 20,
      "age": 39,
      "cum_prem": 100000,
      "cv_basic": 125883.05,
      "cv_total": 125883.05,
      "sa_basic": 80774,
      "death_benefit": 201412.88,
      "increment_amount": 0,
      "cv_increment": 0
    },
    {
      "y": 21,
      "age": 40,
      "cum_prem": 100000,
      "cv_basic": 127653.61,
      "cv_total": 127653.61,
      "sa_basic": 80774,
      "death_benefit": 204245.78,
      "increment_amount": 0,
      "cv_increment": 0
    },
    {
      "y": 22,
      "age": 41,
      "cum_prem": 100000,
      "cv_basic": 129482.34,
      "cv_total": 129482.34,
      "sa_basic": 80774,
      "death_benefit": 181275.28,
      "increment_amount": 0,
      "cv_increment": 0
    },
    {
      "y": 23,
      "age": 42,
      "cum_prem": 100000,
      "cv_basic": 131328.83,
      "cv_total": 131328.83,
      "sa_basic": 80774,
      "death_benefit": 183860.37,
      "increment_amount": 0,
      "cv_increment": 0
    },
    {
      "y": 24,
      "age": 43,
      "cum_prem": 100000,
      "cv_basic": 133193.9,
      "cv_total": 133193.9,
      "sa_basic": 80774,
      "death_benefit": 186471.46,
      "increment_amount": 0,
      "cv_increment": 0
    },
    {
      "y": 25,
      "age": 44,
      "cum_prem": 100000,
      "cv_basic": 135075.94,
      "cv_total": 135075.94,
      "sa_basic": 80774,
      "death_benefit": 189106.32,
      "increment_amount": 0,
      "cv_increment": 0
    },
    {
      "y": 26,
      "age": 45,
      "cum_prem": 100000,
      "cv_basic": 136969.28,
      "cv_total": 136969.28,
      "sa_basic": 80774,
      "death_benefit": 191757,
      "increment_amount": 0,
      "cv_increment": 0
    },
    {
      "y": 27,
      "age": 46,
      "cum_prem": 100000,
      "cv_basic": 138878.78,
      "cv_total": 138878.78,
      "sa_basic": 80774,
      "death_benefit": 194430.3,
      "increment_amount": 0,
      "cv_increment": 0
    },
    {
      "y": 28,
      "age": 47,
      "cum_prem": 100000,
      "cv_basic": 140803.62,
      "cv_total": 140803.62,
      "sa_basic": 80774,
      "death_benefit": 197125.07,
      "increment_amount": 0,
      "cv_increment": 0
    },
    {
      "y": 29,
      "age": 48,
      "cum_prem": 100000,
      "cv_basic": 142742.2,
      "cv_total": 142742.2,
      "sa_basic": 80774,
      "death_benefit": 199839.08,
      "increment_amount": 0,
      "cv_increment": 0
    },
    {
      "y": 30,
      "age": 49,
      "cum_prem": 100000,
      "cv_basic": 144695.31,
      "cv_total": 144695.31,
      "sa_basic": 80774,
      "death_benefit": 202573.44,
      "increment_amount": 0,
      "cv_increment": 0
    },
    {
      "y": 31,
      "age": 50,
      "cum_prem": 100000,
      "cv_basic": 146662.16,
      "cv_total": 146662.16,
      "sa_basic": 80774,
      "death_benefit": 205327.03,
      "increment_amount": 0,
      "cv_increment": 0
    },
    {
      "y": 32,
      "age": 51,
      "cum_prem": 100000,
      "cv_basic": 148750.98,
      "cv_total": 148750.98,
      "sa_basic": 80774,
      "death_benefit": 178501.18,
      "increment_amount": 0,
      "cv_increment": 0
    },
    {
      "y": 33,
      "age": 52,
      "cum_prem": 100000,
      "cv_basic": 150861.6,
      "cv_total": 150861.6,
      "sa_basic": 80774,
      "death_benefit": 181033.92,
      "increment_amount": 0,
      "cv_increment": 0
    },
    {
      "y": 34,
      "age": 53,
      "cum_prem": 100000,
      "cv_basic": 152993.23,
      "cv_total": 152993.23,
      "sa_basic": 80774,
      "death_benefit": 183591.88,
      "increment_amount": 0,
      "cv_increment": 0
    },
    {
      "y": 35,
      "age": 54,
      "cum_prem": 100000,
      "cv_basic": 155145.85,
      "cv_total": 155145.85,
      "sa_basic": 80774,
      "death_benefit": 186175.02,
      "increment_amount": 0,
      "cv_increment": 0
    },
    {
      "y": 36,
      "age": 55,
      "cum_prem": 100000,
      "cv_basic": 157313.02,
      "cv_total": 157313.02,
      "sa_basic": 80774,
      "death_benefit": 188775.63,
      "increment_amount": 0,
      "cv_increment": 0
    },
    {
      "y": 37,
      "age": 56,
      "cum_prem": 100000,
      "cv_basic": 159499.57,
      "cv_total": 159499.57,
      "sa_basic": 80774,
      "death_benefit": 191399.49,
      "increment_amount": 0,
      "cv_increment": 0
    },
    {
      "y": 38,
      "age": 57,
      "cum_prem": 100000,
      "cv_basic": 161703.89,
      "cv_total": 161703.89,
      "sa_basic": 80774,
      "death_benefit": 194044.67,
      "increment_amount": 0,
      "cv_increment": 0
    },
    {
      "y": 39,
      "age": 58,
      "cum_prem": 100000,
      "cv_basic": 163924.37,
      "cv_total": 163924.37,
      "sa_basic": 80774,
      "death_benefit": 196709.25,
      "increment_amount": 0,
      "cv_increment": 0
    },
    {
      "y": 40,
      "age": 59,
      "cum_prem": 100000,
      "cv_basic": 166160.2,
      "cv_total": 166160.2,
      "sa_basic": 80774,
      "death_benefit": 199392.24,
      "increment_amount": 0,
      "cv_increment": 0
    },
    {
      "y": 41,
      "age": 60,
      "cum_prem": 100000,
      "cv_basic": 168400.06,
      "cv_total": 168400.06,
      "sa_basic": 80774,
      "death_benefit": 202080.08,
      "increment_amount": 0,
      "cv_increment": 0
    },
    {
      "y": 42,
      "age": 61,
      "cum_prem": 100000,
      "cv_basic": 170789.35,
      "cv_total": 170789.35,
      "sa_basic": 80774,
      "death_benefit": 187868.29,
      "increment_amount": 0,
      "cv_increment": 0
    },
    {
      "y": 43,
      "age": 62,
      "cum_prem": 100000,
      "cv_basic": 173201.26,
      "cv_total": 173201.26,
      "sa_basic": 80774,
      "death_benefit": 190521.39,
      "increment_amount": 0,
      "cv_increment": 0
    },
    {
      "y": 44,
      "age": 63,
      "cum_prem": 100000,
      "cv_basic": 175634.99,
      "cv_total": 175634.99,
      "sa_basic": 80774,
      "death_benefit": 193198.49,
      "increment_amount": 0,
      "cv_increment": 0
    },
    {
      "y": 45,
      "age": 64,
      "cum_prem": 100000,
      "cv_basic": 178089.71,
      "cv_total": 178089.71,
      "sa_basic": 80774,
      "death_benefit": 195898.69,
      "increment_amount": 0,
      "cv_increment": 0
    },
    {
      "y": 46,
      "age": 65,
      "cum_prem": 100000,
      "cv_basic": 180556.55,
      "cv_total": 180556.55,
      "sa_basic": 80774,
      "death_benefit": 198612.21,
      "increment_amount": 0,
      "cv_increment": 0
    },
    {
      "y": 47,
      "age": 66,
      "cum_prem": 100000,
      "cv_basic": 183039.54,
      "cv_total": 183039.54,
      "sa_basic": 80774,
      "death_benefit": 201343.5,
      "increment_amount": 0,
      "cv_increment": 0
    },
    {
      "y": 48,
      "age": 67,
      "cum_prem": 100000,
      "cv_basic": 185535.45,
      "cv_total": 185535.45,
      "sa_basic": 80774,
      "death_benefit": 204089,
      "increment_amount": 0,
      "cv_increment": 0
    },
    {
      "y": 49,
      "age": 68,
      "cum_prem": 100000,
      "cv_basic": 188041.06,
      "cv_total": 188041.06,
      "sa_basic": 80774,
      "death_benefit": 206845.17,
      "increment_amount": 0,
      "cv_increment": 0
    },
    {
      "y": 50,
      "age": 69,
      "cum_prem": 100000,
      "cv_basic": 190553.94,
      "cv_total": 190553.94,
      "sa_basic": 80774,
      "death_benefit": 209609.34,
      "increment_amount": 0,
      "cv_increment": 0
    },
    {
      "y": 51,
      "age": 70,
      "cum_prem": 100000,
      "cv_basic": 193050.67,
      "cv_total": 193050.67,
      "sa_basic": 80774,
      "death_benefit": 212355.74,
      "increment_amount": 0,
      "cv_increment": 0
    },
    {
      "y": 52,
      "age": 71,
      "cum_prem": 100000,
      "cv_basic": 195866.45,
      "cv_total": 195866.45,
      "sa_basic": 80774,
      "death_benefit": 199783.78,
      "increment_amount": 0,
      "cv_increment": 0
    },
    {
      "y": 53,
      "age": 72,
      "cum_prem": 100000,
      "cv_basic": 198715.35,
      "cv_total": 198715.35,
      "sa_basic": 80774,
      "death_benefit": 202689.66,
      "increment_amount": 0,
      "cv_increment": 0
    },
    {
      "y": 54,
      "age": 73,
      "cum_prem": 100000,
      "cv_basic": 201597.36,
      "cv_total": 201597.36,
      "sa_basic": 80774,
      "death_benefit": 205629.31,
      "increment_amount": 0,
      "cv_increment": 0
    },
    {
      "y": 55,
      "age": 74,
      "cum_prem": 100000,
      "cv_basic": 204511.69,
      "cv_total": 204511.69,
      "sa_basic": 80774,
      "death_benefit": 208601.93,
      "increment_amount": 0,
      "cv_increment": 0
    },
    {
      "y": 56,
      "age": 75,
      "cum_prem": 100000,
      "cv_basic": 207458.33,
      "cv_total": 207458.33,
      "sa_basic": 80774,
      "death_benefit": 211607.5,
      "increment_amount": 0,
      "cv_increment": 0
    },
    {
      "y": 57,
      "age": 76,
      "cum_prem": 100000,
      "cv_basic": 210435.66,
      "cv_total": 210435.66,
      "sa_basic": 80774,
      "death_benefit": 214644.38,
      "increment_amount": 0,
      "cv_increment": 0
    },
    {
      "y": 58,
      "age": 77,
      "cum_prem": 100000,
      "cv_basic": 213442.87,
      "cv_total": 213442.87,
      "sa_basic": 80774,
      "death_benefit": 217711.73,
      "increment_amount": 0,
      "cv_increment": 0
    },
    {
      "y": 59,
      "age": 78,
      "cum_prem": 100000,
      "cv_basic": 216477.55,
      "cv_total": 216477.55,
      "sa_basic": 80774,
      "death_benefit": 220807.11,
      "increment_amount": 0,
      "cv_increment": 0
    },
    {
      "y": 60,
      "age": 79,
      "cum_prem": 100000,
      "cv_basic": 219539.69,
      "cv_total": 219539.69,
      "sa_basic": 80774,
      "death_benefit": 223930.49,
      "increment_amount": 0,
      "cv_increment": 0
    },
    {
      "y": 61,
      "age": 80,
      "cum_prem": 100000,
      "cv_basic": 222626.07,
      "cv_total": 222626.07,
      "sa_basic": 80774,
      "death_benefit": 227078.6,
      "increment_amount": 0,
      "cv_increment": 0
    },
    {
      "y": 62,
      "age": 81,
      "cum_prem": 100000,
      "cv_basic": 225736.67,
      "cv_total": 225736.67,
      "sa_basic": 80774,
      "death_benefit": 230251.41,
      "increment_amount": 0,
      "cv_increment": 0
    },
    {
      "y": 63,
      "age": 82,
      "cum_prem": 100000,
      "cv_basic": 228869.09,
      "cv_total": 228869.09,
      "sa_basic": 80774,
      "death_benefit": 233446.48,
      "increment_amount": 0,
      "cv_increment": 0
    },
    {
      "y": 64,
      "age": 83,
      "cum_prem": 100000,
      "cv_basic": 232020.08,
      "cv_total": 232020.08,
      "sa_basic": 80774,
      "death_benefit": 236660.49,
      "increment_amount": 0,
      "cv_increment": 0
    },
    {
      "y": 65,
      "age": 84,
      "cum_prem": 100000,
      "cv_basic": 235187.23,
      "cv_total": 235187.23,
      "sa_basic": 80774,
      "death_benefit": 239890.98,
      "increment_amount": 0,
      "cv_increment": 0
    },
    {
      "y": 66,
      "age": 85,
      "cum_prem": 100000,
      "cv_basic": 238368.11,
      "cv_total": 238368.11,
      "sa_basic": 80774,
      "death_benefit": 243135.48,
      "increment_amount": 0,
      "cv_increment": 0
    },
    {
      "y": 67,
      "age": 86,
      "cum_prem": 100000,
      "cv_basic": 241557.88,
      "cv_total": 241557.88,
      "sa_basic": 80774,
      "death_benefit": 246389.04,
      "increment_amount": 0,
      "cv_increment": 0
    },
    {
      "y": 68,
      "age": 87,
      "cum_prem": 100000,
      "cv_basic": 244751.68,
      "cv_total": 244751.68,
      "sa_basic": 80774,
      "death_benefit": 249646.72,
      "increment_amount": 0,
      "cv_increment": 0
    },
    {
      "y": 69,
      "age": 88,
      "cum_prem": 100000,
      "cv_basic": 247946.29,
      "cv_total": 247946.29,
      "sa_basic": 80774,
      "death_benefit": 252905.22,
      "increment_amount": 0,
      "cv_increment": 0
    },
    {
      "y": 70,
      "age": 89,
      "cum_prem": 100000,
      "cv_basic": 251138.48,
      "cv_total": 251138.48,
      "sa_basic": 80774,
      "death_benefit": 256161.25,
      "increment_amount": 0,
      "cv_increment": 0
    },
    {
      "y": 71,
      "age": 90,
      "cum_prem": 100000,
      "cv_basic": 254318.55,
      "cv_total": 254318.55,
      "sa_basic": 80774,
      "death_benefit": 259404.93,
      "increment_amount": 0,
      "cv_increment": 0
    },
    {
      "y": 72,
      "age": 91,
      "cum_prem": 100000,
      "cv_basic": 258132.7,
      "cv_total": 258132.7,
      "sa_basic": 80774,
      "death_benefit": 258132.7,
      "increment_amount": 0,
      "cv_increment": 0
    },
    {
      "y": 73,
      "age": 92,
      "cum_prem": 100000,
      "cv_basic": 262003.39,
      "cv_total": 262003.39,
      "sa_basic": 80774,
      "death_benefit": 262003.39,
      "increment_amount": 0,
      "cv_increment": 0
    },
    {
      "y": 74,
      "age": 93,
      "cum_prem": 100000,
      "cv_basic": 265933.05,
      "cv_total": 265933.05,
      "sa_basic": 80774,
      "death_benefit": 265933.05,
      "increment_amount": 0,
      "cv_increment": 0
    },
    {
      "y": 75,
      "age": 94,
      "cum_prem": 100000,
      "cv_basic": 269920.86,
      "cv_total": 269920.86,
      "sa_basic": 80774,
      "death_benefit": 269920.86,
      "increment_amount": 0,
      "cv_increment": 0
    },
    {
      "y": 76,
      "age": 95,
      "cum_prem": 100000,
      "cv_basic": 273967.64,
      "cv_total": 273967.64,
      "sa_basic": 80774,
      "death_benefit": 273967.64,
      "increment_amount": 0,
      "cv_increment": 0
    },
    {
      "y": 77,
      "age": 96,
      "cum_prem": 100000,
      "cv_basic": 278075.8,
      "cv_total": 278075.8,
      "sa_basic": 80774,
      "death_benefit": 278075.8,
      "increment_amount": 0,
      "cv_increment": 0
    },
    {
      "y": 78,
      "age": 97,
      "cum_prem": 100000,
      "cv_basic": 282245.36,
      "cv_total": 282245.36,
      "sa_basic": 80774,
      "death_benefit": 282245.36,
      "increment_amount": 0,
      "cv_increment": 0
    },
    {
      "y": 79,
      "age": 98,
      "cum_prem": 100000,
      "cv_basic": 286477.11,
      "cv_total": 286477.11,
      "sa_basic": 80774,
      "death_benefit": 286477.11,
      "increment_amount": 0,
      "cv_increment": 0
    },
    {
      "y": 80,
      "age": 99,
      "cum_prem": 100000,
      "cv_basic": 290771.86,
      "cv_total": 290771.86,
      "sa_basic": 80774,
      "death_benefit": 290771.86,
      "increment_amount": 0,
      "cv_increment": 0
    },
    {
      "y": 81,
      "age": 100,
      "cum_prem": 100000,
      "cv_basic": 295131.23,
      "cv_total": 295131.23,
      "sa_basic": 80774,
      "death_benefit": 295131.23,
      "increment_amount": 0,
      "cv_increment": 0
    },
    {
      "y": 82,
      "age": 101,
      "cum_prem": 100000,
      "cv_basic": 299555.23,
      "cv_total": 299555.23,
      "sa_basic": 80774,
      "death_benefit": 299555.23,
      "increment_amount": 0,
      "cv_increment": 0
    },
    {
      "y": 83,
      "age": 102,
      "cum_prem": 100000,
      "cv_basic": 304045.45,
      "cv_total": 304045.45,
      "sa_basic": 80774,
      "death_benefit": 304045.45,
      "increment_amount": 0,
      "cv_increment": 0
    },
    {
      "y": 84,
      "age": 103,
      "cum_prem": 100000,
      "cv_basic": 308602.72,
      "cv_total": 308602.72,
      "sa_basic": 80774,
      "death_benefit": 308602.72,
      "increment_amount": 0,
      "cv_increment": 0
    },
    {
      "y": 85,
      "age": 104,
      "cum_prem": 100000,
      "cv_basic": 313228.65,
      "cv_total": 313228.65,
      "sa_basic": 80774,
      "death_benefit": 313228.65,
      "increment_amount": 0,
      "cv_increment": 0
    },
    {
      "y": 86,
      "age": 105,
      "cum_prem": 100000,
      "cv_basic": 317922.43,
      "cv_total": 317922.43,
      "sa_basic": 80774,
      "death_benefit": 317922.43,
      "increment_amount": 0,
      "cv_increment": 0
    },
    {
      "y": 87,
      "age": 106,
      "cum_prem": 100000,
      "cv_basic": 322686.48,
      "cv_total": 322686.48,
      "sa_basic": 80774,
      "death_benefit": 322686.48,
      "increment_amount": 0,
      "cv_increment": 0
    },
    {
      "y": 88,
      "age": 107,
      "cum_prem": 100000,
      "cv_basic": 327521.61,
      "cv_total": 327521.61,
      "sa_basic": 80774,
      "death_benefit": 327521.61,
      "increment_amount": 0,
      "cv_increment": 0
    },
    {
      "y": 89,
      "age": 108,
      "cum_prem": 100000,
      "cv_basic": 332427.82,
      "cv_total": 332427.82,
      "sa_basic": 80774,
      "death_benefit": 332427.82,
      "increment_amount": 0,
      "cv_increment": 0
    },
    {
      "y": 90,
      "age": 109,
      "cum_prem": 100000,
      "cv_basic": 337407.54,
      "cv_total": 337407.54,
      "sa_basic": 80774,
      "death_benefit": 337407.54,
      "increment_amount": 0,
      "cv_increment": 0
    },
    {
      "y": 91,
      "age": 110,
      "cum_prem": 100000,
      "cv_basic": 0,
      "cv_total": 0,
      "sa_basic": 80774,
      "death_benefit": 342449.45,
      "increment_amount": 0,
      "cv_increment": 0
    }
  ],
  "extraction_note": "2026-05-10 重做為躉繳 demo (M20/$100K). PDF 試算日期 115/05/10. 宣告 4.3% / 保證 1.5%. 保險費4.5萬美元(含)~13.5萬美元(不含)，享0.8%保費折扣 (本試算落於此級距). ⚠ xls 因環境缺 xlrd 無法解析,min_sa/max_sa/min_age/max_age 用安全預設,需補 DM. 三方驗證 F=C+D準 自動通過 (Y1-Y90 全表). Y91 為終身年度,F 變祝壽金結構特殊.",
  "source_pdf": "d-吉美得美元利率變動型終身壽險-20260510001826.pdf",
  "extracted_at": "2026-05-09T16:52:12.391789"
}