{
  "meta": {
    "product_id": "6UC4",
    "company": "凱基人壽",
    "product_name": "凱基人壽傳富久安美元利率變動型終身壽險-定期給付型",
    "currency": "USD",
    "period": 20,
    "engine": "twlife_v2_full",
    "product_type": "interest_variable",
    "base_sex": "M",
    "base_age": 36,
    "base_sa": 5207399,
    "base_premium": 200000,
    "discount": 0.025,
    "declared_rate": 0.043,
    "guaranteed_rate": 0.0275,
    "dividend_option": "以繳清保險方式增加保險金額",
    "calc_method": "保額",
    "source_file": "凱基人壽傳富久安美元利率變動型終身壽險-定期給付型_6UC4_20260101-試算表20260110.xlsx",
    "extracted_at": "2026-05-14 v2full-batch2",
    "needs_revalidation": false,
    "notes": "v7 校準對齊 Drew(36 歲男 USD 200k 6年): SA=3342814, prem=200000",
    "verified_against": "Drew 2026-05-14 美元利變非還本 10年",
    "verified_against_20y": "Drew 2026-05-14 美元利變非還本 20年 (sa=9090109 prem=200000)",
    "cross_verified": [
      "美元利變(預定利率) 6年 sa=3342814 prem=200000"
    ],
    "unit_size": 1,
    "v2_full_format": "kgi",
    "granular_sa": true,
    "min_sa": 1,
    "schedule_synth": true,
    "schedule_synth_note": "v55b: cv@y20=174% 異常",
    "gp_age_curve_v65b": "41M=1482510,39F=1789766, mortality_slope=1.04",
    "pv_table_cleared_v69": "147/414 entries had cv > 2000 per 1000 SA, cleared"
  },
  "gp_table": {
    "1000M": 156.0,
    "1001M": 161.0,
    "1002M": 165.0,
    "1003M": 169.0,
    "1004M": 174.0,
    "1005M": 179.0,
    "1006M": 183.0,
    "1007M": 189.0,
    "1008M": 194.0,
    "1009M": 199.0,
    "1010M": 206.0,
    "1011M": 210.0,
    "1012M": 217.0,
    "1013M": 223.0,
    "1014M": 228.0,
    "1015M": 235.0,
    "1016M": 239.0,
    "1017M": 246.0,
    "1018M": 251.0,
    "1019M": 260.0,
    "1020M": 267.0,
    "1021M": 273.0,
    "1022M": 279.0,
    "1023M": 286.0,
    "1024M": 294.0,
    "1025M": 300.0,
    "1026M": 308.0,
    "1027M": 318.0,
    "1028M": 326.0,
    "1029M": 335.0,
    "1030M": 342.0,
    "1031M": 350.0,
    "1032M": 358.0,
    "1033M": 371.0,
    "1034M": 379.0,
    "1035M": 387.0,
    "1036M": 398.0,
    "1037M": 409.0,
    "1038M": 417.0,
    "1039M": 429.0,
    "1040M": 437.0,
    "1041M": 448.0,
    "1042M": 459.0,
    "1043M": 469.0,
    "1044M": 481.0,
    "1045M": 493.0,
    "1046M": 505.0,
    "1047M": 517.0,
    "1048M": 530.0,
    "1049M": 543.0,
    "1050M": 557.0,
    "1051M": 570.0,
    "1052M": 584.0,
    "1053M": 598.0,
    "1054M": 612.0,
    "1055M": 626.0,
    "1056M": 641.0,
    "1057M": 656.0,
    "1058M": 673.0,
    "1059M": 690.0,
    "1060M": 707.0,
    "1061M": 726.0,
    "1062M": 745.0,
    "1063M": 763.0,
    "1064M": 782.0,
    "1065M": 803.0,
    "1066M": 835.0,
    "1067M": 859.0,
    "1068M": 868.0,
    "1069M": 896.0,
    "1070M": 934.0,
    "2000M": 90.0,
    "2001M": 92.0,
    "2002M": 94.0,
    "2003M": 96.0,
    "2004M": 99.0,
    "2005M": 103.0,
    "2006M": 106.0,
    "2007M": 109.0,
    "2008M": 112.0,
    "2009M": 115.0,
    "2010M": 118.0,
    "2011M": 121.0,
    "2012M": 124.0,
    "2013M": 126.0,
    "2014M": 129.0,
    "2015M": 133.0,
    "2016M": 136.0,
    "2017M": 140.0,
    "2018M": 144.0,
    "2019M": 148.0,
    "2020M": 152.0,
    "2021M": 156.0,
    "2022M": 161.0,
    "2023M": 164.0,
    "2024M": 168.0,
    "2025M": 172.0,
    "2026M": 176.0,
    "2027M": 180.0,
    "2028M": 185.0,
    "2029M": 190.0,
    "2030M": 196.0,
    "2031M": 200.0,
    "2032M": 206.0,
    "2033M": 211.0,
    "2034M": 216.0,
    "2035M": 222.0,
    "2036M": 228.0,
    "2037M": 233.0,
    "2038M": 238.0,
    "2039M": 244.0,
    "2040M": 253.0,
    "2041M": 258.0,
    "2042M": 264.0,
    "2043M": 270.0,
    "2044M": 277.0,
    "2045M": 285.0,
    "2046M": 292.0,
    "2047M": 300.0,
    "2048M": 308.0,
    "2049M": 316.0,
    "2050M": 324.0,
    "2051M": 333.0,
    "2052M": 342.0,
    "2053M": 351.0,
    "2054M": 360.0,
    "2055M": 371.0,
    "2056M": 380.0,
    "2057M": 390.0,
    "2058M": 401.0,
    "2059M": 412.0,
    "2060M": 423.0,
    "1000F": 133.0,
    "1001F": 137.0,
    "1002F": 140.0,
    "1003F": 142.0,
    "1004F": 146.0,
    "1005F": 151.0,
    "1006F": 155.0,
    "1007F": 159.0,
    "1008F": 164.0,
    "1009F": 169.0,
    "1010F": 173.0,
    "1011F": 177.0,
    "1012F": 181.0,
    "1013F": 186.0,
    "1014F": 192.0,
    "1015F": 197.0,
    "1016F": 201.0,
    "1017F": 207.0,
    "1018F": 213.0,
    "1019F": 219.0,
    "1020F": 224.0,
    "1021F": 229.0,
    "1022F": 236.0,
    "1023F": 241.0,
    "1024F": 248.0,
    "1025F": 256.0,
    "1026F": 262.0,
    "1027F": 269.0,
    "1028F": 275.0,
    "1029F": 282.0,
    "1030F": 289.0,
    "1031F": 298.0,
    "1032F": 306.0,
    "1033F": 313.0,
    "1034F": 322.0,
    "1035F": 331.0,
    "1036F": 340.0,
    "1037F": 349.0,
    "1038F": 357.0,
    "1039F": 366.0,
    "1040F": 375.0,
    "1041F": 385.0,
    "1042F": 395.0,
    "1043F": 406.0,
    "1044F": 417.0,
    "1045F": 428.0,
    "1046F": 438.0,
    "1047F": 449.0,
    "1048F": 460.0,
    "1049F": 471.0,
    "1050F": 483.0,
    "1051F": 496.0,
    "1052F": 509.0,
    "1053F": 523.0,
    "1054F": 537.0,
    "1055F": 550.0,
    "1056F": 565.0,
    "1057F": 578.0,
    "1058F": 594.0,
    "1059F": 608.0,
    "1060F": 625.0,
    "1061F": 639.0,
    "1062F": 657.0,
    "1063F": 674.0,
    "1064F": 691.0,
    "1065F": 710.0,
    "1066F": 727.0,
    "1067F": 748.0,
    "1068F": 769.0,
    "1069F": 792.0,
    "1070F": 815.0,
    "2000F": 75.0,
    "2001F": 77.0,
    "2002F": 79.0,
    "2003F": 81.0,
    "2004F": 83.0,
    "2005F": 85.0,
    "2006F": 88.0,
    "2007F": 90.0,
    "2008F": 92.0,
    "2009F": 95.0,
    "2010F": 98.0,
    "2011F": 100.0,
    "2012F": 104.0,
    "2013F": 107.0,
    "2014F": 110.0,
    "2015F": 113.0,
    "2016F": 116.0,
    "2017F": 119.0,
    "2018F": 122.0,
    "2019F": 125.0,
    "2020F": 127.0,
    "2021F": 130.0,
    "2022F": 134.0,
    "2023F": 138.0,
    "2024F": 142.0,
    "2025F": 146.0,
    "2026F": 150.0,
    "2027F": 154.0,
    "2028F": 158.0,
    "2029F": 162.0,
    "2030F": 166.0,
    "2031F": 170.0,
    "2032F": 174.0,
    "2033F": 180.0,
    "2034F": 185.0,
    "2035F": 190.0,
    "2036F": 195.0,
    "2037F": 200.0,
    "2038F": 205.0,
    "2039F": 210.0,
    "2040F": 215.0,
    "2041F": 223.0,
    "2042F": 229.0,
    "2043F": 235.0,
    "2044F": 240.0,
    "2045F": 247.0,
    "2046F": 255.0,
    "2047F": 262.0,
    "2048F": 269.0,
    "2049F": 276.0,
    "2050F": 285.0,
    "2051F": 293.0,
    "2052F": 302.0,
    "2053F": 311.0,
    "2054F": 320.0,
    "2055F": 329.0,
    "2056F": 340.0,
    "2057F": 350.0,
    "2058F": 360.0,
    "2059F": 372.0,
    "2060F": 399.0,
    "0600M": 13.65,
    "0601M": 14.19,
    "0602M": 14.76,
    "0603M": 15.35,
    "0604M": 15.96,
    "0605M": 16.6,
    "0606M": 17.27,
    "0607M": 17.96,
    "0608M": 18.68,
    "0609M": 19.42,
    "0610M": 20.2,
    "0611M": 21.01,
    "0612M": 21.85,
    "0613M": 22.72,
    "0614M": 23.63,
    "0615M": 24.58,
    "0616M": 25.56,
    "0617M": 26.58,
    "0618M": 27.64,
    "0619M": 28.75,
    "0620M": 29.9,
    "0621M": 31.1,
    "0622M": 32.34,
    "0623M": 33.63,
    "0624M": 34.98,
    "0625M": 36.38,
    "0626M": 37.83,
    "0627M": 39.35,
    "0628M": 40.92,
    "0629M": 42.56,
    "0630M": 44.26,
    "0631M": 46.03,
    "0632M": 47.87,
    "0633M": 49.79,
    "0634M": 51.78,
    "0635M": 53.85,
    "0636M": 56.0,
    "0637M": 58.24,
    "0638M": 60.57,
    "0639M": 62.99,
    "0640M": 65.51,
    "0641M": 68.13,
    "0642M": 70.86,
    "0643M": 73.69,
    "0644M": 76.64,
    "0645M": 79.71,
    "0646M": 82.9,
    "0647M": 86.21,
    "0648M": 89.66,
    "0649M": 93.25,
    "0650M": 96.98,
    "0651M": 100.86,
    "0652M": 104.89,
    "0653M": 109.09,
    "0654M": 113.45,
    "0655M": 117.99,
    "0656M": 122.71,
    "0657M": 127.61,
    "0658M": 132.72,
    "0659M": 138.03,
    "0660M": 143.55,
    "0661M": 149.29,
    "0662M": 155.26,
    "0663M": 161.47,
    "0664M": 167.93,
    "0665M": 174.65,
    "0666M": 181.64,
    "0667M": 188.9,
    "0668M": 196.46,
    "0669M": 204.32,
    "0670M": 212.49,
    "0671M": 220.99,
    "0672M": 229.83,
    "0673M": 239.02,
    "0674M": 248.58,
    "0675M": 258.52,
    "0676M": 268.86,
    "0677M": 279.62,
    "0678M": 290.8,
    "0679M": 302.44,
    "0680M": 314.53,
    "0681M": 327.12,
    "0682M": 340.2,
    "0683M": 353.81,
    "0684M": 367.96,
    "0685M": 382.68,
    "0686M": 397.99,
    "0687M": 413.91,
    "0688M": 430.46,
    "0689M": 447.68,
    "0690M": 465.59,
    "0600F": 12.23,
    "0601F": 12.71,
    "0602F": 13.22,
    "0603F": 13.75,
    "0604F": 14.3,
    "0605F": 14.87,
    "0606F": 15.47,
    "0607F": 16.09,
    "0608F": 16.74,
    "0609F": 17.4,
    "0610F": 18.1,
    "0611F": 18.82,
    "0612F": 19.58,
    "0613F": 20.36,
    "0614F": 21.17,
    "0615F": 22.02,
    "0616F": 22.9,
    "0617F": 23.81,
    "0618F": 24.76,
    "0619F": 25.76,
    "0620F": 26.79,
    "0621F": 27.86,
    "0622F": 28.97,
    "0623F": 30.13,
    "0624F": 31.34,
    "0625F": 32.59,
    "0626F": 33.89,
    "0627F": 35.25,
    "0628F": 36.66,
    "0629F": 38.13,
    "0630F": 39.65,
    "0631F": 41.24,
    "0632F": 42.89,
    "0633F": 44.61,
    "0634F": 46.39,
    "0635F": 48.25,
    "0636F": 50.17,
    "0637F": 52.18,
    "0638F": 54.27,
    "0639F": 56.43,
    "0640F": 58.69,
    "0641F": 61.04,
    "0642F": 63.48,
    "0643F": 66.02,
    "0644F": 68.66,
    "0645F": 71.41,
    "0646F": 74.27,
    "0647F": 77.24,
    "0648F": 80.33,
    "0649F": 83.54,
    "0650F": 86.89,
    "0651F": 90.36,
    "0652F": 93.97,
    "0653F": 97.74,
    "0654F": 101.64,
    "0655F": 105.71,
    "0656F": 109.94,
    "0657F": 114.33,
    "0658F": 118.91,
    "0659F": 123.66,
    "0660F": 128.61,
    "0661F": 133.75,
    "0662F": 139.1,
    "0663F": 144.66,
    "0664F": 150.45,
    "0665F": 156.47,
    "0666F": 162.73,
    "0667F": 169.24,
    "0668F": 176.01,
    "0669F": 183.05,
    "0670F": 190.37,
    "0671F": 197.99,
    "0672F": 205.91,
    "0673F": 214.14,
    "0674F": 222.71,
    "0675F": 231.61,
    "0676F": 240.88,
    "0677F": 250.52,
    "0678F": 260.53,
    "0679F": 270.96,
    "0680F": 281.79,
    "0681F": 293.07,
    "0682F": 304.79,
    "0683F": 316.98,
    "0684F": 329.66,
    "0685F": 342.85,
    "0686F": 356.57,
    "0687F": 370.83,
    "0688F": 385.66,
    "0689F": 401.08,
    "0690F": 417.13
  },
  "pv_table": {},
  "cv_table": {},
  "schedule": [
    {
      "y": 1,
      "age": 40,
      "cum_prem": 30000,
      "cv_total": 13492,
      "cv_basic": 13219,
      "sa_basic": 455843,
      "increment_amount": 807,
      "cv_increment": 273,
      "death_benefit": 455843
    },
    {
      "y": 2,
      "age": 41,
      "cum_prem": 60000,
      "cv_total": 36435,
      "cv_basic": 35419,
      "sa_basic": 455843,
      "increment_amount": 2930,
      "cv_increment": 1016,
      "death_benefit": 456650
    },
    {
      "y": 3,
      "age": 42,
      "cum_prem": 90000,
      "cv_total": 60471,
      "cv_basic": 58211,
      "sa_basic": 455843,
      "increment_amount": 6363,
      "cv_increment": 2260,
      "death_benefit": 458773
    },
    {
      "y": 4,
      "age": 43,
      "cum_prem": 120000,
      "cv_total": 85727,
      "cv_basic": 81687,
      "sa_basic": 455843,
      "increment_amount": 11101,
      "cv_increment": 4040,
      "death_benefit": 462206
    },
    {
      "y": 5,
      "age": 44,
      "cum_prem": 150000,
      "cv_total": 119208,
      "cv_basic": 112821,
      "sa_basic": 455843,
      "increment_amount": 17138,
      "cv_increment": 6387,
      "death_benefit": 466944
    },
    {
      "y": 6,
      "age": 45,
      "cum_prem": 180000,
      "cv_total": 181651,
      "cv_basic": 172309,
      "sa_basic": 455843,
      "increment_amount": 24469,
      "cv_increment": 9342,
      "death_benefit": 472981
    },
    {
      "y": 7,
      "age": 46,
      "cum_prem": 180000,
      "cv_total": 190713,
      "cv_basic": 178235,
      "sa_basic": 455843,
      "increment_amount": 31914,
      "cv_increment": 12478,
      "death_benefit": 480312
    },
    {
      "y": 8,
      "age": 47,
      "cum_prem": 180000,
      "cv_total": 198275,
      "cv_basic": 182474,
      "sa_basic": 455843,
      "increment_amount": 39473,
      "cv_increment": 15801,
      "death_benefit": 487757
    },
    {
      "y": 9,
      "age": 48,
      "cum_prem": 180000,
      "cv_total": 206126,
      "cv_basic": 186804,
      "sa_basic": 455843,
      "increment_amount": 47150,
      "cv_increment": 19322,
      "death_benefit": 495316
    },
    {
      "y": 10,
      "age": 49,
      "cum_prem": 180000,
      "cv_total": 214276,
      "cv_basic": 191226,
      "sa_basic": 455843,
      "increment_amount": 54947,
      "cv_increment": 23050,
      "death_benefit": 502993
    },
    {
      "y": 11,
      "age": 50,
      "cum_prem": 180000,
      "cv_total": 222681,
      "cv_basic": 195693,
      "sa_basic": 455843,
      "increment_amount": 62865,
      "cv_increment": 26988,
      "death_benefit": 510790
    },
    {
      "y": 12,
      "age": 51,
      "cum_prem": 180000,
      "cv_total": 231401,
      "cv_basic": 200252,
      "sa_basic": 455843,
      "increment_amount": 70905,
      "cv_increment": 31149,
      "death_benefit": 518708
    },
    {
      "y": 13,
      "age": 52,
      "cum_prem": 180000,
      "cv_total": 240443,
      "cv_basic": 204901,
      "sa_basic": 455843,
      "increment_amount": 79070,
      "cv_increment": 35542,
      "death_benefit": 526748
    },
    {
      "y": 14,
      "age": 53,
      "cum_prem": 180000,
      "cv_total": 249766,
      "cv_basic": 209597,
      "sa_basic": 455843,
      "increment_amount": 87361,
      "cv_increment": 40169,
      "death_benefit": 534913
    },
    {
      "y": 15,
      "age": 54,
      "cum_prem": 180000,
      "cv_total": 259429,
      "cv_basic": 214383,
      "sa_basic": 455843,
      "increment_amount": 95781,
      "cv_increment": 45046,
      "death_benefit": 543204
    },
    {
      "y": 16,
      "age": 55,
      "cum_prem": 180000,
      "cv_total": 269444,
      "cv_basic": 219260,
      "sa_basic": 455843,
      "increment_amount": 104332,
      "cv_increment": 50184,
      "death_benefit": 551624
    },
    {
      "y": 17,
      "age": 56,
      "cum_prem": 180000,
      "cv_total": 279821,
      "cv_basic": 224229,
      "sa_basic": 455843,
      "increment_amount": 113015,
      "cv_increment": 55592,
      "death_benefit": 560175
    },
    {
      "y": 18,
      "age": 57,
      "cum_prem": 180000,
      "cv_total": 290512,
      "cv_basic": 229243,
      "sa_basic": 455843,
      "increment_amount": 121832,
      "cv_increment": 61269,
      "death_benefit": 568858
    },
    {
      "y": 19,
      "age": 58,
      "cum_prem": 180000,
      "cv_total": 301586,
      "cv_basic": 234349,
      "sa_basic": 455843,
      "increment_amount": 130786,
      "cv_increment": 67237,
      "death_benefit": 577675
    },
    {
      "y": 20,
      "age": 59,
      "cum_prem": 180000,
      "cv_total": 312992,
      "cv_basic": 239500,
      "sa_basic": 455843,
      "increment_amount": 139878,
      "cv_increment": 73492,
      "death_benefit": 586629
    },
    {
      "y": 21,
      "age": 60,
      "cum_prem": 180000,
      "cv_total": 324861,
      "cv_basic": 244788,
      "sa_basic": 455843,
      "increment_amount": 149111,
      "cv_increment": 80073,
      "death_benefit": 595721
    },
    {
      "y": 22,
      "age": 61,
      "cum_prem": 180000,
      "cv_total": 337083,
      "cv_basic": 250121,
      "sa_basic": 455843,
      "increment_amount": 158488,
      "cv_increment": 86962,
      "death_benefit": 604954
    },
    {
      "y": 23,
      "age": 62,
      "cum_prem": 180000,
      "cv_total": 349732,
      "cv_basic": 255546,
      "sa_basic": 455843,
      "increment_amount": 168010,
      "cv_increment": 94186,
      "death_benefit": 614331
    },
    {
      "y": 24,
      "age": 63,
      "cum_prem": 180000,
      "cv_total": 362756,
      "cv_basic": 261016,
      "sa_basic": 455843,
      "increment_amount": 177680,
      "cv_increment": 101740,
      "death_benefit": 623853
    },
    {
      "y": 25,
      "age": 64,
      "cum_prem": 180000,
      "cv_total": 376162,
      "cv_basic": 266531,
      "sa_basic": 455843,
      "increment_amount": 187500,
      "cv_increment": 109631,
      "death_benefit": 633523
    },
    {
      "y": 26,
      "age": 65,
      "cum_prem": 180000,
      "cv_total": 390029,
      "cv_basic": 272138,
      "sa_basic": 455843,
      "increment_amount": 197472,
      "cv_increment": 117891,
      "death_benefit": 643343
    },
    {
      "y": 27,
      "age": 66,
      "cum_prem": 180000,
      "cv_total": 404301,
      "cv_basic": 277791,
      "sa_basic": 455843,
      "increment_amount": 207598,
      "cv_increment": 126510,
      "death_benefit": 653315
    },
    {
      "y": 28,
      "age": 67,
      "cum_prem": 180000,
      "cv_total": 418989,
      "cv_basic": 283489,
      "sa_basic": 455843,
      "increment_amount": 217881,
      "cv_increment": 135500,
      "death_benefit": 663441
    },
    {
      "y": 29,
      "age": 68,
      "cum_prem": 180000,
      "cv_total": 434036,
      "cv_basic": 289187,
      "sa_basic": 455843,
      "increment_amount": 228324,
      "cv_increment": 144849,
      "death_benefit": 673724
    },
    {
      "y": 30,
      "age": 69,
      "cum_prem": 180000,
      "cv_total": 449516,
      "cv_basic": 294930,
      "sa_basic": 455843,
      "increment_amount": 238928,
      "cv_increment": 154586,
      "death_benefit": 684167
    },
    {
      "y": 31,
      "age": 70,
      "cum_prem": 180000,
      "cv_total": 465374,
      "cv_basic": 300674,
      "sa_basic": 455843,
      "increment_amount": 249697,
      "cv_increment": 164700,
      "death_benefit": 694771
    },
    {
      "y": 32,
      "age": 71,
      "cum_prem": 180000,
      "cv_total": 481616,
      "cv_basic": 306418,
      "sa_basic": 455843,
      "increment_amount": 260633,
      "cv_increment": 175198,
      "death_benefit": 705540
    },
    {
      "y": 33,
      "age": 72,
      "cum_prem": 180000,
      "cv_total": 498247,
      "cv_basic": 312161,
      "sa_basic": 455843,
      "increment_amount": 271738,
      "cv_increment": 186086,
      "death_benefit": 716476
    },
    {
      "y": 34,
      "age": 73,
      "cum_prem": 180000,
      "cv_total": 515206,
      "cv_basic": 317859,
      "sa_basic": 455843,
      "increment_amount": 283016,
      "cv_increment": 197347,
      "death_benefit": 727581
    },
    {
      "y": 35,
      "age": 74,
      "cum_prem": 180000,
      "cv_total": 532421,
      "cv_basic": 323466,
      "sa_basic": 455843,
      "increment_amount": 294469,
      "cv_increment": 208955,
      "death_benefit": 738859
    },
    {
      "y": 36,
      "age": 75,
      "cum_prem": 180000,
      "cv_total": 549969,
      "cv_basic": 329027,
      "sa_basic": 455843,
      "increment_amount": 306098,
      "cv_increment": 220942,
      "death_benefit": 750312
    },
    {
      "y": 37,
      "age": 76,
      "cum_prem": 180000,
      "cv_total": 567856,
      "cv_basic": 334543,
      "sa_basic": 455843,
      "increment_amount": 317908,
      "cv_increment": 233313,
      "death_benefit": 761941
    },
    {
      "y": 38,
      "age": 77,
      "cum_prem": 180000,
      "cv_total": 586007,
      "cv_basic": 339968,
      "sa_basic": 455843,
      "increment_amount": 329900,
      "cv_increment": 246039,
      "death_benefit": 773751
    },
    {
      "y": 39,
      "age": 78,
      "cum_prem": 180000,
      "cv_total": 604346,
      "cv_basic": 345255,
      "sa_basic": 455843,
      "increment_amount": 342079,
      "cv_increment": 259091,
      "death_benefit": 785743
    },
    {
      "y": 40,
      "age": 79,
      "cum_prem": 180000,
      "cv_total": 623032,
      "cv_basic": 350498,
      "sa_basic": 455843,
      "increment_amount": 354447,
      "cv_increment": 272534,
      "death_benefit": 797922
    },
    {
      "y": 41,
      "age": 80,
      "cum_prem": 180000,
      "cv_total": 641905,
      "cv_basic": 355603,
      "sa_basic": 455843,
      "increment_amount": 367007,
      "cv_increment": 286302,
      "death_benefit": 810290
    },
    {
      "y": 42,
      "age": 81,
      "cum_prem": 180000,
      "cv_total": 661046,
      "cv_basic": 360617,
      "sa_basic": 455843,
      "increment_amount": 379761,
      "cv_increment": 300429,
      "death_benefit": 822850
    },
    {
      "y": 43,
      "age": 82,
      "cum_prem": 180000,
      "cv_total": 680372,
      "cv_basic": 365495,
      "sa_basic": 455843,
      "increment_amount": 392713,
      "cv_increment": 314877,
      "death_benefit": 835604
    },
    {
      "y": 44,
      "age": 83,
      "cum_prem": 180000,
      "cv_total": 699966,
      "cv_basic": 370281,
      "sa_basic": 455843,
      "increment_amount": 405866,
      "cv_increment": 329685,
      "death_benefit": 848556
    },
    {
      "y": 45,
      "age": 84,
      "cum_prem": 180000,
      "cv_total": 719742,
      "cv_basic": 374931,
      "sa_basic": 455843,
      "increment_amount": 419223,
      "cv_increment": 344811,
      "death_benefit": 861709
    },
    {
      "y": 46,
      "age": 85,
      "cum_prem": 180000,
      "cv_total": 739695,
      "cv_basic": 379444,
      "sa_basic": 455843,
      "increment_amount": 432786,
      "cv_increment": 360251,
      "death_benefit": 875066
    },
    {
      "y": 47,
      "age": 86,
      "cum_prem": 180000,
      "cv_total": 759824,
      "cv_basic": 383820,
      "sa_basic": 455843,
      "increment_amount": 446560,
      "cv_increment": 376004,
      "death_benefit": 888629
    },
    {
      "y": 48,
      "age": 87,
      "cum_prem": 180000,
      "cv_total": 780216,
      "cv_basic": 388105,
      "sa_basic": 455843,
      "increment_amount": 460548,
      "cv_increment": 392111,
      "death_benefit": 902403
    },
    {
      "y": 49,
      "age": 88,
      "cum_prem": 180000,
      "cv_total": 800778,
      "cv_basic": 392253,
      "sa_basic": 455843,
      "increment_amount": 474753,
      "cv_increment": 408525,
      "death_benefit": 916391
    },
    {
      "y": 50,
      "age": 89,
      "cum_prem": 180000,
      "cv_total": 821413,
      "cv_basic": 396219,
      "sa_basic": 455843,
      "increment_amount": 489178,
      "cv_increment": 425194,
      "death_benefit": 930596
    },
    {
      "y": 51,
      "age": 90,
      "cum_prem": 180000,
      "cv_total": 842108,
      "cv_basic": 400002,
      "sa_basic": 455843,
      "increment_amount": 503825,
      "cv_increment": 442106,
      "death_benefit": 945021
    },
    {
      "y": 52,
      "age": 91,
      "cum_prem": 180000,
      "cv_total": 862958,
      "cv_basic": 403649,
      "sa_basic": 455843,
      "increment_amount": 518700,
      "cv_increment": 459309,
      "death_benefit": 959668
    },
    {
      "y": 53,
      "age": 92,
      "cum_prem": 180000,
      "cv_total": 883855,
      "cv_basic": 407113,
      "sa_basic": 455843,
      "increment_amount": 533806,
      "cv_increment": 476742,
      "death_benefit": 974543
    },
    {
      "y": 54,
      "age": 93,
      "cum_prem": 180000,
      "cv_total": 904892,
      "cv_basic": 410441,
      "sa_basic": 455843,
      "increment_amount": 549146,
      "cv_increment": 494451,
      "death_benefit": 989649
    },
    {
      "y": 55,
      "age": 94,
      "cum_prem": 180000,
      "cv_total": 925959,
      "cv_basic": 413586,
      "sa_basic": 455843,
      "increment_amount": 564723,
      "cv_increment": 512373,
      "death_benefit": 1004989
    },
    {
      "y": 56,
      "age": 95,
      "cum_prem": 180000,
      "cv_total": 947048,
      "cv_basic": 416549,
      "sa_basic": 455843,
      "increment_amount": 580542,
      "cv_increment": 530499,
      "death_benefit": 1020566
    },
    {
      "y": 57,
      "age": 96,
      "cum_prem": 180000,
      "cv_total": 968254,
      "cv_basic": 419376,
      "sa_basic": 455843,
      "increment_amount": 596606,
      "cv_increment": 548878,
      "death_benefit": 1036385
    },
    {
      "y": 58,
      "age": 97,
      "cum_prem": 180000,
      "cv_total": 989567,
      "cv_basic": 422065,
      "sa_basic": 455843,
      "increment_amount": 612919,
      "cv_increment": 567502,
      "death_benefit": 1052449
    },
    {
      "y": 59,
      "age": 98,
      "cum_prem": 180000,
      "cv_total": 1010873,
      "cv_basic": 424572,
      "sa_basic": 455843,
      "increment_amount": 629484,
      "cv_increment": 586301,
      "death_benefit": 1068762
    },
    {
      "y": 60,
      "age": 99,
      "cum_prem": 180000,
      "cv_total": 1032274,
      "cv_basic": 426943,
      "sa_basic": 455843,
      "increment_amount": 646307,
      "cv_increment": 605331,
      "death_benefit": 1085327
    },
    {
      "y": 61,
      "age": 100,
      "cum_prem": 180000,
      "cv_total": 1053646,
      "cv_basic": 429131,
      "sa_basic": 455843,
      "increment_amount": 663390,
      "cv_increment": 624515,
      "death_benefit": 1102150
    },
    {
      "y": 62,
      "age": 101,
      "cum_prem": 180000,
      "cv_total": 1075205,
      "cv_basic": 431227,
      "sa_basic": 455843,
      "increment_amount": 680738,
      "cv_increment": 643978,
      "death_benefit": 1119233
    },
    {
      "y": 63,
      "age": 102,
      "cum_prem": 180000,
      "cv_total": 1096835,
      "cv_basic": 433188,
      "sa_basic": 455843,
      "increment_amount": 698355,
      "cv_increment": 663647,
      "death_benefit": 1136581
    },
    {
      "y": 64,
      "age": 103,
      "cum_prem": 180000,
      "cv_total": 1118641,
      "cv_basic": 435057,
      "sa_basic": 455843,
      "increment_amount": 716245,
      "cv_increment": 683584,
      "death_benefit": 1154198
    },
    {
      "y": 65,
      "age": 104,
      "cum_prem": 180000,
      "cv_total": 1140741,
      "cv_basic": 436880,
      "sa_basic": 455843,
      "increment_amount": 734413,
      "cv_increment": 703861,
      "death_benefit": 1172088
    },
    {
      "y": 66,
      "age": 105,
      "cum_prem": 180000,
      "cv_total": 1163379,
      "cv_basic": 438749,
      "sa_basic": 455843,
      "increment_amount": 752862,
      "cv_increment": 724630,
      "death_benefit": 1190256
    },
    {
      "y": 67,
      "age": 106,
      "cum_prem": 180000,
      "cv_total": 1186934,
      "cv_basic": 440800,
      "sa_basic": 455843,
      "increment_amount": 771597,
      "cv_increment": 746134,
      "death_benefit": 1208705
    },
    {
      "y": 68,
      "age": 107,
      "cum_prem": 180000,
      "cv_total": 1212936,
      "cv_basic": 443581,
      "sa_basic": 455843,
      "increment_amount": 790623,
      "cv_increment": 769355,
      "death_benefit": 1227440
    },
    {
      "y": 69,
      "age": 108,
      "cum_prem": 180000,
      "cv_total": 1243255,
      "cv_basic": 447729,
      "sa_basic": 455843,
      "increment_amount": 809943,
      "cv_increment": 795526,
      "death_benefit": 1246466
    },
    {
      "y": 70,
      "age": 109,
      "cum_prem": 180000,
      "cv_total": 1265786,
      "cv_basic": 455843,
      "sa_basic": 455843,
      "increment_amount": 809943,
      "cv_increment": 809943,
      "death_benefit": 1265786
    }
  ],
  "schedule_at_base": [
    {
      "y": 1,
      "age": 36,
      "cum_prem": 200000,
      "cv_basic": 81225.0,
      "cv_total": 85500.0,
      "death_benefit": 5207399
    },
    {
      "y": 2,
      "age": 37,
      "cum_prem": 400000,
      "cv_basic": 172900.0,
      "cv_total": 182000.0,
      "death_benefit": 5207399
    },
    {
      "y": 3,
      "age": 38,
      "cum_prem": 600000,
      "cv_basic": 275025.0,
      "cv_total": 289500.0,
      "death_benefit": 5207399
    },
    {
      "y": 4,
      "age": 39,
      "cum_prem": 800000,
      "cv_basic": 387600.0,
      "cv_total": 408000.0,
      "death_benefit": 5207399
    },
    {
      "y": 5,
      "age": 40,
      "cum_prem": 1000000,
      "cv_basic": 510625.0,
      "cv_total": 537500.0,
      "death_benefit": 5207399
    },
    {
      "y": 6,
      "age": 41,
      "cum_prem": 1200000,
      "cv_basic": 644100.0,
      "cv_total": 678000.0,
      "death_benefit": 5207399
    },
    {
      "y": 7,
      "age": 42,
      "cum_prem": 1400000,
      "cv_basic": 788025.0,
      "cv_total": 829500.0,
      "death_benefit": 5207399
    },
    {
      "y": 8,
      "age": 43,
      "cum_prem": 1600000,
      "cv_basic": 942400.0,
      "cv_total": 992000.0,
      "death_benefit": 5207399
    },
    {
      "y": 9,
      "age": 44,
      "cum_prem": 1800000,
      "cv_basic": 1107225.0,
      "cv_total": 1165500.0,
      "death_benefit": 5207399
    },
    {
      "y": 10,
      "age": 45,
      "cum_prem": 2000000,
      "cv_basic": 1282500.0,
      "cv_total": 1350000.0,
      "death_benefit": 5207399
    },
    {
      "y": 11,
      "age": 46,
      "cum_prem": 2200000,
      "cv_basic": 1468225.0,
      "cv_total": 1545500.0,
      "death_benefit": 5207399
    },
    {
      "y": 12,
      "age": 47,
      "cum_prem": 2400000,
      "cv_basic": 1664400.0,
      "cv_total": 1752000.0,
      "death_benefit": 5207399
    },
    {
      "y": 13,
      "age": 48,
      "cum_prem": 2600000,
      "cv_basic": 1871025.0,
      "cv_total": 1969500.0,
      "death_benefit": 5207399
    },
    {
      "y": 14,
      "age": 49,
      "cum_prem": 2800000,
      "cv_basic": 2088100.0,
      "cv_total": 2198000.0,
      "death_benefit": 5207399
    },
    {
      "y": 15,
      "age": 50,
      "cum_prem": 3000000,
      "cv_basic": 2315625.0,
      "cv_total": 2437500.0,
      "death_benefit": 5207399
    },
    {
      "y": 16,
      "age": 51,
      "cum_prem": 3200000,
      "cv_basic": 2553600.0,
      "cv_total": 2688000.0,
      "death_benefit": 5207399
    },
    {
      "y": 17,
      "age": 52,
      "cum_prem": 3400000,
      "cv_basic": 2802025.0,
      "cv_total": 2949500.0,
      "death_benefit": 5207399
    },
    {
      "y": 18,
      "age": 53,
      "cum_prem": 3600000,
      "cv_basic": 3060900.0,
      "cv_total": 3222000.0,
      "death_benefit": 5207399
    },
    {
      "y": 19,
      "age": 54,
      "cum_prem": 3800000,
      "cv_basic": 3330225.0,
      "cv_total": 3505500.0,
      "death_benefit": 5207399
    },
    {
      "y": 20,
      "age": 55,
      "cum_prem": 4000000,
      "cv_basic": 3610000.0,
      "cv_total": 3800000.0,
      "death_benefit": 5207399
    }
  ]
}